datazeus/__init__.py
datazeus/classifiers.py
datazeus/main.py
datazeus-0.0.1.dist-info/LICENSE
datazeus-0.0.1.dist-info/METADATA
datazeus-0.0.1.dist-info/WHEEL
datazeus-0.0.1.dist-info/top_level.txt
datazeus-0.0.1.dist-info/RECORD
